nostr_toolkit/__init__.py
nostr_toolkit/domain/__init__.py
nostr_toolkit/domain/client.py
nostr_toolkit/domain/events.py
nostr_toolkit/domain/exceptions.py
nostr_toolkit/domain/primitives.py
nostr_toolkit/domain/relay.py
nostr_toolkit/domain/suscriptions.py
nostr_toolkit/infra/__init__.py
nostr_toolkit/infra/serializers.py
nostr_toolkit/tests/__init__.py
nostr_toolkit/tests/domain/__init__.py
nostr_toolkit/tests/domain/test_event.py
nostr_toolkit/tests/infra/__init__.py
nostr_toolkit/tests/infra/conftest.py
nostr_toolkit/tests/infra/test_serializers.py
nostr_toolkit-0.0.1.dist-info/LICENSE
nostr_toolkit-0.0.1.dist-info/METADATA
nostr_toolkit-0.0.1.dist-info/WHEEL
nostr_toolkit-0.0.1.dist-info/top_level.txt
nostr_toolkit-0.0.1.dist-info/RECORD
