Metadata-Version: 2.1
Name: nostr-toolkit
Version: 0.0.1
Summary: An object-oriented library to build on top of nostr.
Author-email: zilt0id <zilt0id@noreply.codeberg.org>
License: The MIT License (MIT)
Project-URL: homepage, https://codeberg.org/zilt0id/nostr_toolkit
Keywords: nostr
Classifier: License :: OSI Approved :: MIT License
Classifier: Programming Language :: Python
Classifier: Programming Language :: Python :: 3
Requires-Python: >=3.10
License-File: LICENSE
Requires-Dist: typing-extensions
Provides-Extra: dev
Requires-Dist: pytest ; extra == 'dev'
